README.md
setup.py
htmltable_df/__init__.py
htmltable_df/extractor.py
htmltable_df.egg-info/PKG-INFO
htmltable_df.egg-info/SOURCES.txt
htmltable_df.egg-info/dependency_links.txt
htmltable_df.egg-info/requires.txt
htmltable_df.egg-info/top_level.txt