Metadata-Version: 1.1
Name: htmltable-df
Version: 1.0.1
Summary: A python library for extracting data from html table
Home-page: https://github.com/shiaukuan/htmltable-df
Author: shiaukuan
Author-email: kuan60508@gmail.com
License: MIT
Keywords: html table pyquery crawler scrape
Platform: UNKNOWN
Classifier: License :: OSI Approved :: MIT License
Classifier: Programming Language :: Python :: 2
Classifier: Programming Language :: Python :: 2.7
Classifier: Programming Language :: Python :: 3
Classifier: Programming Language :: Python :: 3.5
